{"siyuangao@outlook.com":{"name":"Siyuan Gao","username":"siyuangao@outlook.com","password":"123456","phone":"6191234567","picture":"https://scontent.xx.fbcdn.net/v/t1.0-1/p480x480/14063962_308761462805639_5534274990633654594_n.jpg?oh=7c4c5f0d7fd8086d6e2821cccb5b69e6&oe=5B397327","recording":[{"date":"1519702627312"}],"family":[{"name":"Kevin"},{"name":"Sarah"}],"routine":[{"time":"06:00 PM","repeat":"daily","id":"0"},{"time":"04:15 PM","repeat":"daily","id":"1"},{"time":"01:00 AM","repeat":"monthly","id":"2"}]}}